para-fpax-CORDIC/para_cordic_src_previos/para_S/clockgen.vhd
-- Clock Generator
library IEEE;
use IEEE.std_logic_1164.all;


entity clkGen is
  port (clk : out std_logic);
end clkGen;

architecture behavior of clkGen is

constant clk_period : time := 10 ps;

begin
  clkgen : process
  
  begin
  
  	clk <= '0';
    wait for clk_period/2;  
    clk <= '1';
    wait for clk_period/2;  
  end process clkgen;
end behavior;

BasicCordic/basicCordic.vhd
library IEEE;
    use IEEE.std_logic_1164.all;
    use IEEE.numeric_std.all;
    use IEEE.fixed_float_types.all;
    use IEEE.fixed_pkg.all;
    
entity basic_cordic is
    GENERIC (
        NMB_ITERATIONS  :   integer := 30;
        PRECISION_FP    :   integer := 31
    );
    
port (
        angle_i : in sfixed (1 downto - PRECISION_FP);
        start_i : in std_logic;
        clock_i : in std_logic;
        sin_o : out sfixed (1 downto - PRECISION_FP);
        cos_o : out sfixed (1 downto - PRECISION_FP);
        rdy_o : out std_logic);
    end basic_cordic;
    
architecture behavior of basic_cordic is
    type rotAngles is array (0 to 29) of sfixed(1 downto - PRECISION_FP);
    constant LUTangles : rotAngles := (
		to_sfixed(0.785398163397448, 1, - PRECISION_FP),
		to_sfixed(0.463647609000806, 1, - PRECISION_FP),
		to_sfixed(0.244978663126864, 1, - PRECISION_FP),
		to_sfixed(0.124354994546761, 1, - PRECISION_FP),
		to_sfixed(0.062418809995957, 1, - PRECISION_FP),
		to_sfixed(0.031239833430268, 1, - PRECISION_FP),
		to_sfixed(0.015623728620477, 1, - PRECISION_FP),
		to_sfixed(0.007812341060101, 1, - PRECISION_FP),
		to_sfixed(0.003906230131967, 1, - PRECISION_FP),
		to_sfixed(0.001953122516479, 1, - PRECISION_FP),
		to_sfixed(0.000976562189559, 1, - PRECISION_FP),
		to_sfixed(0.000488281211195, 1, - PRECISION_FP),
		to_sfixed(0.000244140620149, 1, - PRECISION_FP),
		to_sfixed(0.000122070311894, 1, - PRECISION_FP),
		to_sfixed(0.000061035156174, 1, - PRECISION_FP),
		to_sfixed(0.000030517578116, 1, - PRECISION_FP),
		to_sfixed(0.000015258789061, 1, - PRECISION_FP),
		to_sfixed(0.000007629394531, 1, - PRECISION_FP),
		to_sfixed(0.000003814697266, 1, - PRECISION_FP),
		to_sfixed(0.000001907348633, 1, - PRECISION_FP),
		to_sfixed(0.000000953674316, 1, - PRECISION_FP),
		to_sfixed(0.000000476837158, 1, - PRECISION_FP),
		to_sfixed(0.000000238418579, 1, - PRECISION_FP),
		to_sfixed(0.000000119209290, 1, - PRECISION_FP),
		to_sfixed(0.000000059604645, 1, - PRECISION_FP),
		to_sfixed(0.000000029802322, 1, - PRECISION_FP),
		to_sfixed(0.000000014901161, 1, - PRECISION_FP),
		to_sfixed(0.000000007450581, 1, - PRECISION_FP),
		to_sfixed(0.000000003725290, 1, - PRECISION_FP),
		to_sfixed(0.000000001862645, 1, - PRECISION_FP)
);

    type mul_factor is array (0 to 29) of sfixed(1 downto - PRECISION_FP);
    constant LUT_K : mul_factor := (
		to_sfixed(0.707106781186547, 1, - PRECISION_FP),
		to_sfixed(0.632455532033676, 1, - PRECISION_FP),
		to_sfixed(0.613571991077896, 1, - PRECISION_FP),
		to_sfixed(0.608833912517752, 1, - PRECISION_FP),
		to_sfixed(0.607648256256168, 1, - PRECISION_FP),
		to_sfixed(0.607351770141296, 1, - PRECISION_FP),
		to_sfixed(0.607277644093526, 1, - PRECISION_FP),
		to_sfixed(0.607259112298893, 1, - PRECISION_FP),
		to_sfixed(0.607254479332562, 1, - PRECISION_FP),
		to_sfixed(0.607253321089875, 1, - PRECISION_FP),
		to_sfixed(0.607253031529134, 1, - PRECISION_FP),
		to_sfixed(0.607252959138945, 1, - PRECISION_FP),
		to_sfixed(0.607252941041397, 1, - PRECISION_FP),
		to_sfixed(0.607252936517010, 1, - PRECISION_FP),
		to_sfixed(0.607252935385914, 1, - PRECISION_FP),
		to_sfixed(0.607252935103139, 1, - PRECISION_FP),
		to_sfixed(0.607252935032446, 1, - PRECISION_FP),
		to_sfixed(0.607252935014772, 1, - PRECISION_FP),
		to_sfixed(0.607252935010354, 1, - PRECISION_FP),
		to_sfixed(0.607252935009249, 1, - PRECISION_FP),
		to_sfixed(0.607252935008973, 1, - PRECISION_FP),
		to_sfixed(0.607252935008904, 1, - PRECISION_FP),
		to_sfixed(0.607252935008887, 1, - PRECISION_FP),
		to_sfixed(0.607252935008883, 1, - PRECISION_FP),
		to_sfixed(0.607252935008882, 1, - PRECISION_FP),
		to_sfixed(0.607252935008881, 1, - PRECISION_FP),
		to_sfixed(0.607252935008881, 1, - PRECISION_FP),
		to_sfixed(0.607252935008881, 1, - PRECISION_FP),
		to_sfixed(0.607252935008881, 1, - PRECISION_FP),
		to_sfixed(0.607252935008881, 1, - PRECISION_FP)
);

begin
    algorithm : process(clock_i)
        variable state : integer := 0;
        variable z : sfixed (1 downto - PRECISION_FP);
        variable x : sfixed (1 downto - PRECISION_FP);
        variable y : sfixed (1 downto - PRECISION_FP);
        variable bufx : sfixed (1 downto - PRECISION_FP);
        variable bufy : sfixed (1 downto - PRECISION_FP);
    begin
        if rising_edge(clock_i) then
            if start_i = '1' then
                if state >= NMB_ITERATIONS then
                    -- finished with the calculation
                    sin_o <= y;
                    cos_o <= x;
                    rdy_o <= '1';
                else
                    -- perform the cordic in rotation mode to calculate sin and cos
                    if state = 0 then
                        -- if the input angle is negativ, make it positive and save the sign
                        z := resize(arg => angle_i, size_res => z);
                        -- perfrom the first rotation/iteration
                        if z > 0 then
                            -- input angle is positive
                            x := LUT_K(NMB_ITERATIONS-1);
                            y := x;
                            z := resize(arg => z - LUTangles(0), size_res => z);
                        elsif z < 0 then
                            x := LUT_K(NMB_ITERATIONS-1);
                            y := resize(-x, 1, -PRECISION_FP);
                            z := resize(arg => z + LUTangles(0), size_res => z);
                        else
                            -- input was 0, therefore stop the algorithm right away
                            state := NMB_ITERATIONS;
                            x := to_sfixed(1, 1, -PRECISION_FP);
                            y := to_sfixed(0, 1, -PRECISION_FP);
                        end if;
                    else
                        -- perfrom iterations
                        if z > 0 then
                            bufx := x;
                            if y < 0 then
                                bufy := resize(arg => -y, size_res => bufy);
                                x := resize(arg => (x + (bufy srl state)), size_res => x);
                            else
                                x := resize(arg => (x - (y srl state)), size_res => x);
                            end if;
                            if bufx < 0 then
                                bufx := resize(arg => -bufx, size_res => bufx);
                                y := resize(arg => (y - (bufx srl state)), size_res => y);
                            else
                                y := resize(arg => (y + (bufx srl state)), size_res => y);
                            end if;
                            z := resize(arg => z - LUTangles(state), size_res => z);
                        else
                            bufx := x;
                            if y < 0 then
                                bufy := resize(arg => -y, size_res => bufy);
                                x := resize(arg => (x - (bufy srl state)), size_res => x);
                            else
                                x := resize(arg => (x + (y srl state)), size_res => x);
                            end if;
                            if bufx < 0 then
                                bufx := resize(arg => -bufx, size_res => bufx);
                                y := resize(arg => (y + (bufx srl state)), size_res => y);
                            else
                                y := resize(arg => (y - (bufx srl state)), size_res => y);
                            end if;
                            z := resize(arg => z + LUTangles(state), size_res => z);
                        end if;
                    end if;
                    sin_o <= y;
                    cos_o <= x;
                    state := state + 1;
                end if;
            else
                -- inactive state, set all outputs to their inital values
                rdy_o <= '0';
                state := 0;
                sin_o <= LUT_K(NMB_ITERATIONS-1);
                cos_o <= to_sfixed(0, 1, -PRECISION_FP);        
            end if;
        end if;
    end process algorithm;
end behavior;

VHDL_implementations/BasicCordic/tb_basicCordic1.vhd
library IEEE;
    use IEEE.std_logic_1164.all;
    use IEEE.numeric_std.all;
    use IEEE.fixed_float_types.all;
    use IEEE.fixed_pkg.all;
    use STD.textio.all;
    use ieee.std_logic_textio.all;
    
entity testbench is
    end testbench;
    
    architecture tb of testbench is
    
    component basic_cordic is
    GENERIC (
        NMB_ITERATIONS  :   integer := 40;
        PRECISION_FP    :   integer := 31
    );
    
port (
        angle_i : in sfixed (1 downto - PRECISION_FP);
        start_i : in std_logic;
        clock_i : in std_logic;
        sin_o : out sfixed (1 downto - PRECISION_FP);
        cos_o : out sfixed (1 downto - PRECISION_FP);
        rdy_o : out std_logic);
    end component;
    
component clkGen is
    port (clk : out std_logic);
    end component;
    
signal sig_clk, sig_start, sig_rdy: std_logic;
    signal sin_out, cos_out : sfixed (1 downto -31);
    signal sig_in : sfixed (1 downto -31);

begin
       
    -- connect DUT with tb signals
    DUT:
        basic_cordic
        generic map(NMB_ITERATIONS => 40, PRECISION_FP => 31)
        port map(
        angle_i => sig_in,
        start_i => sig_start,
        clock_i => sig_clk,
        rdy_o => sig_rdy,
        sin_o => sin_out,
        cos_o => cos_out);
            
    -- clockgenerator
    mClkGen : clkGen port map(
        clk => sig_clk
    );
        
    -- apply a test angle as input
    stimuli: process
    begin
        sig_in <= to_sfixed(-0.785398, 1, - 31);
        sig_start <= '1';
        wait until sig_rdy = '1';
        --report "sin:" & to_string(to_integer(sin_out));
        --report "sin:" & to_string(to_integer(sin_out(4 downto 1)));
        std.textio.write(std.textio.output, to_string((sin_out)) & LF);
        std.textio.write(std.textio.output, to_string((sin_out)));
        sig_start <= '0';
        sig_in <= to_sfixed(-0.523599, 1, - 31);
        sig_start <= '1';
        wait until sig_rdy = '1';
        sig_start <= '0';
        sig_in <= to_sfixed(-0.392699, 1, - 31);
        sig_start <= '1';
        wait until sig_rdy = '1';
        sig_start <= '0';
        sig_in <= to_sfixed(0.01, 1, - 31);
        sig_start <= '1';
        wait until sig_rdy = '1';
        sig_start <= '0';
        sig_in <= to_sfixed(0.392699, 1, - 31);
        sig_start <= '1';
        wait until sig_rdy = '1';
        sig_start <= '0';
        sig_in <= to_sfixed(0.523599, 1, - 31);
        sig_start <= '1';
        wait until sig_rdy = '1';
        sig_start <= '0';
        sig_in <= to_sfixed(0.392699, 1, - 31);
        sig_start <= '1';
        wait until sig_rdy = '1';
    end process stimuli;
        
    --assert false report "end of simulation reached ...";
end;

BasicCordic/dumb.vcd
$date
  Sat Feb 13 19:18:40 2021
$end
$version
  GHDL v0
$end
$timescale
  1 fs
$end
$scope module standard $end
$upscope $end
$scope module textio $end
$upscope $end
$scope module std_logic_1164 $end
$upscope $end
$scope module numeric_std $end
$upscope $end
$scope module fixed_float_types $end
$upscope $end
$scope module math_real $end
$upscope $end
$scope module std_logic_textio $end
$upscope $end
$scope module env $end
$upscope $end
$scope module testbench $end
$var reg 1 ! sig_clk $end
$var reg 1 " sig_start $end
$var reg 1 # sig_rdy $end
$var reg 25 $ sin_out[1:-23] $end
$var reg 25 % cos_out[1:-23] $end
$var reg 25 & sig_in[1:-23] $end
$scope module dut $end
$var reg 25 ' angle_i[1:-23] $end
$var reg 1 ( start_i $end
$var reg 1 ) clock_i $end
$var reg 25 * sin_o[1:-23] $end
$var reg 25 + cos_o[1:-23] $end
$var reg 1 , rdy_o $end
$upscope $end
$scope module mclkgen $end
$var reg 1 - clk $end
$upscope $end
$upscope $end
$enddefinitions $end
#0
0!
1"
U#
bUUUUUUUUUUUUUUUUUUUUUUUUU $
bUUUUUUUUUUUUUUUUUUUUUUUUU %
b1100110110111100000010011 &
b1100110110111100000010011 '
1(
0)
bUUUUUUUUUUUUUUUUUUUUUUUUU *
bUUUUUUUUUUUUUUUUUUUUUUUUU +
U,
0-
#5000000
1!
b1101100100100010110000110 $
b0010011011011101001111010 %
1)
b1101100100100010110000110 *
b0010011011011101001111010 +
1-
#10000000
0!
0)
0-
#15000000
1!
b1100010110110100001001001 $
b0001001101101110100111101 %
1)
b1100010110110100001001001 *
b0001001101101110100111101 +
1-
#20000000
0!
0)
0-
#25000000
1!
b1100101010001111110011000 $
b0010001000000001100101010 %
1)
b1100101010001111110011000 *
b0010001000000001100101010 +
1-
#30000000
0!
0)
0-
#35000000
1!
b1100111011001111111111101 $
b0010100010101111100110111 %
1)
b1100111011001111111111101 *
b0010100010101111100110111 +
1-
#40000000
0!
0)
0-
#45000000
1!
b1101000101011010111110000 $
b0010101111000010100110111 %
1)
b1101000101011010111110000 *
b0010101111000010100110111 +
1-
#50000000
0!
0)
0-
#55000000
1!
b1101001010111001000011001 $
b0010110100110111110000111 %
1)
b1101001010111001000011001 *
b0010110100110111110000111 +
1-
#60000000
0!
0)
0-
#65000000
1!
b1101001101101101111010111 $
b0010110111101100110111110 %
1)
b1101001101101101111010111 *
b0010110111101100110111110 +
1-
#70000000
0!
0)
0-
#75000000
1!
b1101001100010010000100100 $
b0010110110010011101110110 %
1)
b1101001100010010000100100 *
b0010110110010011101110110 +
1-
#80000000
0!
0)
0-
#85000000
1!
b1101001011100100011111101 $
b0010110101100110110011011 %
1)
b1101001011100100011111101 *
b0010110101100110110011011 +
1-
#90000000
0!
0)
0-
#95000000
1!
b1101001011001101110010111 $
b0010110101010000010000000 %
1)
b1101001011001101110010111 *
b0010110101010000010000000 +
1-
#100000000
0!
0)
0-
#105000000
1!
0"
1#
0(
1)
1,
1-
#110000000
0!
0)
0-
#115000000
1!
0#
b0010011011011101001111010 $
b0000000000000000000000000 %
1)
b0010011011011101001111010 *
b0000000000000000000000000 +
0,
1-
#120000000
0!
0)
0-
#125000000
1!
1"
b1101100100100010110000110 $
b0010011011011101001111010 %
b1100111010111101011001011 &
b1100111010111101011001011 '
1(
1)
b1101100100100010110000110 *
b0010011011011101001111010 +
1-
#130000000
0!
0)
0-
#135000000
1!
b1110110010010001011000011 $
b0011101001001011110110111 %
1)
b1110110010010001011000011 *
b0011101001001011110110111 +
1-
#140000000
0!
0)
0-
#145000000
1!
b1101110111111110011010110 $
b0011010101110000001101000 %
1)
b1101110111111110011010110 *
b0011010101110000001101000 +
1-
#150000000
0!
0)
0-
#155000000
1!
b1101011101010000011001001 $
b0011000100110000000000011 %
1)
b1101011101010000011001001 *
b0011000100110000000000011 +
1-
#160000000
0!
0)
0-
#165000000
1!
b1101010000111101011001001 $
b0010111010100101000010000 %
1)
b1101010000111101011001001 *
b0010111010100101000010000 +
1-
#170000000
0!
0)
0-
#175000000
1!
b1101001011001000001111001 $
b0010110101000110111100111 %
1)
b1101001011001000001111001 *
b0010110101000110111100111 +
1-
#180000000
0!
0)
0-
#185000000
1!
b1101001101111101010110000 $
b0010110111111011110100101 %
1)
b1101001101111101010110000 *
b0010110111111011110100101 +
1-
#190000000
0!
0)
0-
#195000000
1!
b1101001100100001011000001 $
b0010110110100010110011011 %
1)
b1101001100100001011000001 *
b0010110110100010110011011 +
1-
#200000000
0!
0)
0-
#205000000
1!
b1101001101001111000000110 $
b0010110111001111101011000 %
1)
b1101001101001111000000110 *
b0010110111001111101011000 +
1-
#210000000
0!
0)
0-
#215000000
1!
b1101001101100101111010101 $
b0010110111100110000001000 %
1)
b1101001101100101111010101 *
b0010110111100110000001000 +
1-
#220000000
0!
0)
0-
#225000000
1!
0"
1#
0(
1)
1,
1-
#230000000
0!
0)
0-
#235000000
1!
0#
b0010011011011101001111010 $
b0000000000000000000000000 %
1)
b0010011011011101001111010 *
b0000000000000000000000000 +
0,
1-
#240000000
0!
0)
0-
#245000000
1!
1"
b1101100100100010110000110 $
b0010011011011101001111010 %
b1100111110111110110000011 &
b1100111110111110110000011 '
1(
1)
b1101100100100010110000110 *
b0010011011011101001111010 +
1-
#250000000
0!
0)
0-
#255000000
1!
b1110110010010001011000011 $
b0011101001001011110110111 %
1)
b1110110010010001011000011 *
b0011101001001011110110111 +
1-
#260000000
0!
0)
0-
#265000000
1!
b1101110111111110011010110 $
b0011010101110000001101000 %
1)
b1101110111111110011010110 *
b0011010101110000001101000 +
1-
#270000000
0!
0)
0-
#275000000
1!
b1101011101010000011001001 $
b0011000100110000000000011 %
1)
b1101011101010000011001001 *
b0011000100110000000000011 +
1-
#280000000
0!
0)
0-
#285000000
1!
b1101010000111101011001001 $
b0010111010100101000010000 %
1)
b1101010000111101011001001 *
b0010111010100101000010000 +
1-
#290000000
0!
0)
0-
#295000000
1!
b1101001011001000001111001 $
b0010110101000110111100111 %
1)
b1101001011001000001111001 *
b0010110101000110111100111 +
1-
#300000000
0!
0)
0-
#305000000
1!
b1101001101111101010110000 $
b0010110111111011110100101 %
1)
b1101001101111101010110000 *
b0010110111111011110100101 +
1-
#310000000
0!
0)
0-
#315000000
1!
b1101001111011001010011111 $
b0010111001010100110101111 %
1)
b1101001111011001010011111 *
b0010111001010100110101111 +
1-
#320000000
0!
0)
0-
#325000000
1!
b1101010000000111101001000 $
b0010111010000000111111100 %
1)
b1101010000000111101001000 *
b0010111010000000111111100 +
1-
#330000000
0!
0)
0-
#335000000
1!
b1101010000011110111001000 $
b0010111010010110111110100 %
1)
b1101010000011110111001000 *
b0010111010010110111110100 +
1-
#340000000
0!
0)
0-
#345000000
1!
0"
1#
0(
1)
1,
1-
#350000000
0!
0)
0-
#355000000
1!
0#
b0010011011011101001111010 $
b0000000000000000000000000 %
1)
b0010011011011101001111010 *
b0000000000000000000000000 +
0,
1-
#360000000
0!
0)
0-
#365000000
1!
1"
b1101100100100010110000110 $
b0010011011011101001111010 %
b1101000011000000000111011 &
b1101000011000000000111011 '
1(
1)
b1101100100100010110000110 *
b0010011011011101001111010 +
1-
#370000000
0!
0)
0-
#375000000
1!
b1110110010010001011000011 $
b0011101001001011110110111 %
1)
b1110110010010001011000011 *
b0011101001001011110110111 +
1-
#380000000
0!
0)
0-
#385000000
1!
b1101110111111110011010110 $
b0011010101110000001101000 %
1)
b1101110111111110011010110 *
b0011010101110000001101000 +
1-
#390000000
0!
0)
0-
#395000000
1!
b1101011101010000011001001 $
b0011000100110000000000011 %
1)
b1101011101010000011001001 *
b0011000100110000000000011 +
1-
#400000000
0!
0)
0-
#405000000
1!
b1101010000111101011001001 $
b0010111010100101000010000 %
1)
b1101010000111101011001001 *
b0010111010100101000010000 +
1-
#410000000
0!
0)
0-
#415000000
1!
b1101010110110010100011001 $
b0011000000000011000111001 %
1)
b1101010110110010100011001 *
b0011000000000011000111001 +
1-
#420000000
0!
0)
0-
#425000000
1!
b1101010011110010100000001 $
b0010111101011001111001110 %
1)
b1101010011110010100000001 *
b0010111101011001111001110 +
1-
#430000000
0!
0)
0-
#435000000
1!
b1101010010010011110011010 $
b0010111100000011110011001 %
1)
b1101010010010011110011010 *
b0010111100000011110011001 +
1-
#440000000
0!
0)
0-
#445000000
1!
b1101010011000010110100001 $
b0010111100101111001110001 %
1)
b1101010011000010110100001 *
b0010111100101111001110001 +
1-
#450000000
0!
0)
0-
#455000000
1!
b1101010011011010011010000 $
b0010111101000100110101110 %
1)
b1101010011011010011010000 *
b0010111101000100110101110 +
1-
#460000000
0!
0)
0-
#465000000
1!
0"
1#
0(
1)
1,
1-
#470000000
0!
0)
0-
#475000000
1!
0#
b0010011011011101001111010 $
b0000000000000000000000000 %
1)
b0010011011011101001111010 *
b0000000000000000000000000 +
0,
1-
#480000000
0!
0)
0-
#485000000
1!
1"
b1101100100100010110000110 $
b0010011011011101001111010 %
b1101000111000001011110010 &
b1101000111000001011110010 '
1(
1)
b1101100100100010110000110 *
b0010011011011101001111010 +
1-
#490000000
0!
0)
0-
#495000000
1!
b1110110010010001011000011 $
b0011101001001011110110111 %
1)
b1110110010010001011000011 *
b0011101001001011110110111 +
1-
#500000000
0!
0)
0-
#505000000
1!
b1101110111111110011010110 $
b0011010101110000001101000 %
1)
b1101110111111110011010110 *
b0011010101110000001101000 +
1-
#510000000
0!
0)
0-
#515000000
1!
b1101011101010000011001001 $
b0011000100110000000000011 %
1)
b1101011101010000011001001 *
b0011000100110000000000011 +
1-
#520000000
0!
0)
0-
#525000000
1!
b1101010000111101011001001 $
b0010111010100101000010000 %
1)
b1101010000111101011001001 *
b0010111010100101000010000 +
1-
#530000000
0!
0)
0-
#535000000
1!
b1101010110110010100011001 $
b0011000000000011000111001 %
1)
b1101010110110010100011001 *
b0011000000000011000111001 +
1-
#540000000
0!
0)
0-
#545000000
1!
b1101010011110010100000001 $
b0010111101011001111001110 %
1)
b1101010011110010100000001 *
b0010111101011001111001110 +
1-
#550000000
0!
0)
0-
#555000000
1!
b1101010101010001001101000 $
b0010111110110000000000011 %
1)
b1101010101010001001101000 *
b0010111110110000000000011 +
1-
#560000000
0!
0)
0-
#565000000
1!
b1101010110000000111001000 $
b0010111111011010101100000 %
1)
b1101010110000000111001000 *
b0010111111011010101100000 +
1-
#570000000
0!
0)
0-
#575000000
1!
b1101010110011000110100010 $
b0010111111101111111011111 %
1)
b1101010110011000110100010 *
b0010111111101111111011111 +
1-
#580000000
0!
0)
0-
#585000000
1!
0"
1#
0(
1)
1,
1-
#590000000
0!
0)
0-
#595000000
1!
0#
b0010011011011101001111010 $
b0000000000000000000000000 %
1)
b0010011011011101001111010 *
b0000000000000000000000000 +
0,
1-
#600000000
0!
0)
0-
#605000000
1!
1"
b1101100100100010110000110 $
b0010011011011101001111010 %
b1101001011000010110101010 &
b1101001011000010110101010 '
1(
1)
b1101100100100010110000110 *
b0010011011011101001111010 +
1-
#610000000
0!
0)
0-
#615000000
1!
b1110110010010001011000011 $
b0011101001001011110110111 %
1)
b1110110010010001011000011 *
b0011101001001011110110111 +
1-
#620000000
0!
0)
0-
#625000000
1!
b1101110111111110011010110 $
b0011010101110000001101000 %
1)
b1101110111111110011010110 *
b0011010101110000001101000 +
1-
#630000000
0!
0)
0-
#635000000
1!
b1101011101010000011001001 $
b0011000100110000000000011 %
1)
b1101011101010000011001001 *
b0011000100110000000000011 +
1-
#640000000
0!
0)
0-
#645000000
1!
b1101010000111101011001001 $
b0010111010100101000010000 %
1)
b1101010000111101011001001 *
b0010111010100101000010000 +
1-
#650000000
0!
0)
0-
#655000000
1!
b1101010110110010100011001 $
b0011000000000011000111001 %
1)
b1101010110110010100011001 *
b0011000000000011000111001 +
1-
#660000000
0!
0)
0-
#665000000
1!
b1101011001110010100110001 $
b0011000010101100010100100 %
1)
b1101011001110010100110001 *
b0011000010101100010100100 +
1-
#670000000
0!
0)
0-
#675000000
1!
b1101011000010001010000000 $
b0011000001011001001101111 %
1)
b1101011000010001010000000 *
b0011000001011001001101111 +
1-
#680000000
0!
0)
0-
#685000000
1!
b1101011001000001100110010 $
b0011000010000011001001100 %
1)
b1101011001000001100110010 *
b0011000010000011001001100 +
1-
#690000000
0!
0)
0-
#695000000
1!
b1101011001011001110110101 $
b0011000010011000000001010 %
1)
b1101011001011001110110101 *
b0011000010011000000001010 +
1-
#700000000
0!
0)
0-
#705000000
1!
0"
1#
0(
1)
1,
1-
#710000000
0!
0)
0-
#715000000
1!
0#
b0010011011011101001111010 $
b0000000000000000000000000 %
1)
b0010011011011101001111010 *
b0000000000000000000000000 +
0,
1-
#720000000
0!
0)
0-
#725000000
1!
1"
b1101100100100010110000110 $
b0010011011011101001111010 %
b1101001111000100001100010 &
b1101001111000100001100010 '
1(
1)
b1101100100100010110000110 *
b0010011011011101001111010 +
1-
#730000000
0!
0)
0-
#735000000
1!
b1110110010010001011000011 $
b0011101001001011110110111 %
1)
b1110110010010001011000011 *
b0011101001001011110110111 +
1-
#740000000
0!
0)
0-
#745000000
1!
b1101110111111110011010110 $
b0011010101110000001101000 %
1)
b1101110111111110011010110 *
b0011010101110000001101000 +
1-
#750000000
0!
0)
0-
#755000000
1!
b1101011101010000011001001 $
b0011000100110000000000011 %
1)
b1101011101010000011001001 *
b0011000100110000000000011 +
1-
#760000000
0!
0)
0-
#765000000
1!
b1101010000111101011001001 $
b0010111010100101000010000 %
1)
b1101010000111101011001001 *
b0010111010100101000010000 +
1-
#770000000
0!
0)
0-
#775000000
1!
b1101010110110010100011001 $
b0011000000000011000111001 %
1)
b1101010110110010100011001 *
b0011000000000011000111001 +
1-
#780000000
0!
0)
0-
#785000000
1!
b1101011001110010100110001 $
b0011000010101100010100100 %
1)
b1101011001110010100110001 *
b0011000010101100010100100 +
1-
#790000000
0!
0)
0-
#795000000
1!
b1101011011010011111100010 $
b0011000011111111011011001 %
1)
b1101011011010011111100010 *
b0011000011111111011011001 +
1-
#800000000
0!
0)
0-
#805000000
1!
b1101011100000100111100000 $
b0011000100101000100110001 %
1)
b1101011100000100111100000 *
b0011000100101000100110001 +
1-
#810000000
0!
0)
0-
#815000000
1!
b1101011100011101100001000 $
b0011000100111101000101100 %
1)
b1101011100011101100001000 *
b0011000100111101000101100 +
1-
#820000000
0!
0)
0-
#825000000
1!
0"
1#
0(
1)
1,
1-
#830000000
0!
0)
0-
#835000000
1!
0#
b0010011011011101001111010 $
b0000000000000000000000000 %
1)
b0010011011011101001111010 *
b0000000000000000000000000 +
0,
1-
#840000000
0!
0)
0-
#845000000
1!
1"
b1101100100100010110000110 $
b0010011011011101001111010 %
b1101010011000101100011010 &
b1101010011000101100011010 '
1(
1)
b1101100100100010110000110 *
b0010011011011101001111010 +
1-
#850000000
0!
0)
0-
#855000000
1!
b1110110010010001011000011 $
b0011101001001011110110111 %
1)
b1110110010010001011000011 *
b0011101001001011110110111 +
1-
#860000000
0!
0)
0-
#865000000
1!
b1101110111111110011010110 $
b0011010101110000001101000 %
1)
b1101110111111110011010110 *
b0011010101110000001101000 +
1-
#870000000
0!
0)
0-
#875000000
1!
b1101011101010000011001001 $
b0011000100110000000000011 %
1)
b1101011101010000011001001 *
b0011000100110000000000011 +
1-
#880000000
0!
0)
0-
#885000000
1!
b1101101001100011011001001 $
b0011001110111010111110110 %
1)
b1101101001100011011001001 *
b0011001110111010111110110 +
1-
#890000000
0!
0)
0-
#895000000
1!
b1101100011000101100011010 $
b0011001010001110000101101 %
1)
b1101100011000101100011010 *
b0011001010001110000101101 +
1-
#900000000
0!
0)
0-
#905000000
1!
b1101011111111011010101010 $
b0011000111110001001011010 %
1)
b1101011111111011010101010 *
b0011000111110001001011010 +
1-
#910000000
0!
0)
0-
#915000000
1!
b1101100001011111001101110 $
b0011001001000001001101100 %
1)
b1101100001011111001101110 *
b0011001001000001001101100 +
1-
#920000000
0!
0)
0-
#925000000
1!
b1101100000101100111101100 $
b0011001000011001100101011 %
1)
b1101100000101100111101100 *
b0011001000011001100101011 +
1-
#930000000
0!
0)
0-
#935000000
1!
b1101100000010011111010011 $
b0011001000000101101011000 %
1)
b1101100000010011111010011 *
b0011001000000101101011000 +
1-
#940000000
0!
0)
0-
#945000000
1!
0"
1#
0(
1)
1,
1-
#950000000
0!
0)
0-
#955000000
1!
0#
b0010011011011101001111010 $
b0000000000000000000000000 %
1)
b0010011011011101001111010 *
b0000000000000000000000000 +
0,
1-
#960000000
0!
0)
0-
#965000000
1!
1"
b1101100100100010110000110 $
b0010011011011101001111010 %
b1101010111000110111010010 &
b1101010111000110111010010 '
1(
1)
b1101100100100010110000110 *
b0010011011011101001111010 +
1-
#970000000
0!
0)
0-
#975000000
1!
b1110110010010001011000011 $
b0011101001001011110110111 %
1)
b1110110010010001011000011 *
b0011101001001011110110111 +
1-
#980000000
0!
0)
0-
#985000000
1!
b1101110111111110011010110 $
b0011010101110000001101000 %
1)
b1101110111111110011010110 *
b0011010101110000001101000 +
1-
#990000000
0!
0)
0-
#995000000
1!
b1101011101010000011001001 $
b0011000100110000000000011 %
1)
b1101011101010000011001001 *
b0011000100110000000000011 +
1-
#1000000000
0!
0)
0-
#1005000000
1!
b1101101001100011011001001 $
b0011001110111010111110110 %
1)
b1101101001100011011001001 *
b0011001110111010111110110 +
1-
#1010000000
0!
0)
0-
#1015000000
1!
b1101100011000101100011010 $
b0011001010001110000101101 %
1)
b1101100011000101100011010 *
b0011001010001110000101101 +
1-
#1020000000
0!
0)
0-
#1025000000
1!
b1101100110001111110001010 $
b0011001100101011000000000 %
1)
b1101100110001111110001010 *
b0011001100101011000000000 +
1-
#1030000000
0!
0)
0-
#1035000000
1!
b1101100100101001011011110 $
b0011001011011110001000000 %
1)
b1101100100101001011011110 *
b0011001011011110001000000 +
1-
#1040000000
0!
0)
0-
#1045000000
1!
b1101100011110110100100010 $
b0011001010110111010010011 %
1)
b1101100011110110100100010 *
b0011001010110111010010011 +
1-
#1050000000
0!
0)
0-
#1055000000
1!
b1101100011011101001101011 $
b0011001010100011110001010 %
1)
b1101100011011101001101011 *
b0011001010100011110001010 +
1-
#1060000000
0!
0)
0-
#1065000000
1!
0"
1#
0(
1)
1,
1-
#1070000000
0!
0)
0-
#1075000000
1!
0#
b0010011011011101001111010 $
b0000000000000000000000000 %
1)
b0010011011011101001111010 *
b0000000000000000000000000 +
0,
1-
#1080000000
0!
0)
0-
#1085000000
1!
1"
b1101100100100010110000110 $
b0010011011011101001111010 %
b1101011011001000010001010 &
b1101011011001000010001010 '
1(
1)
b1101100100100010110000110 *
b0010011011011101001111010 +
1-
#1090000000
0!
0)
0-
#1095000000
1!
b1110110010010001011000011 $
b0011101001001011110110111 %
1)
b1110110010010001011000011 *
b0011101001001011110110111 +
1-
#1100000000
0!
0)
0-
#1105000000
1!
b1101110111111110011010110 $
b0011010101110000001101000 %
1)
b1101110111111110011010110 *
b0011010101110000001101000 +
1-
#1110000000
0!
0)
0-
#1115000000
1!
b1101011101010000011001001 $
b0011000100110000000000011 %
1)
b1101011101010000011001001 *
b0011000100110000000000011 +
1-
#1120000000
0!
0)
0-
#1125000000
1!
b1101101001100011011001001 $
b0011001110111010111110110 %
1)
b1101101001100011011001001 *
b0011001110111010111110110 +
1-
#1130000000
0!
0)
0-
#1135000000
1!
b1101100011000101100011010 $
b0011001010001110000101101 %
1)
b1101100011000101100011010 *
b0011001010001110000101101 +
1-
#1140000000
0!
0)
0-
#1145000000
1!
b1101100110001111110001010 $
b0011001100101011000000000 %
1)
b1101100110001111110001010 *
b0011001100101011000000000 +
1-
#1150000000
0!
0)
0-
#1155000000
1!
b1101100111110110000110110 $
b0011001101110111111000000 %
1)
b1101100111110110000110110 *
b0011001101110111111000000 +
1-
#1160000000
0!
0)
0-
